prompt_maker/__init__.py
prompt_maker/_modidx.py
prompt_maker/core.py
prompt_maker-0.0.4.dist-info/licenses/LICENSE
prompt_maker-0.0.4.dist-info/METADATA
prompt_maker-0.0.4.dist-info/WHEEL
prompt_maker-0.0.4.dist-info/entry_points.txt
prompt_maker-0.0.4.dist-info/top_level.txt
prompt_maker-0.0.4.dist-info/RECORD
