Metadata-Version: 2.4
Name: prompt_maker
Version: 0.0.4
Summary: prompt maker to library using best practices.
Home-page: https://github.com/Gaurav-Adlakha/prompt_maker
Author: Gaurav-Adlakha
Author-email: gauravadlakha1509@gmail.com
License: Apache Software License 2.0
Keywords: nbdev jupyter notebook python
Classifier: Development Status :: 4 - Beta
Classifier: Intended Audience :: Developers
Classifier: Natural Language :: English
Classifier: Programming Language :: Python :: 3.9
Classifier: Programming Language :: Python :: 3.10
Classifier: Programming Language :: Python :: 3.11
Classifier: Programming Language :: Python :: 3.12
Classifier: License :: OSI Approved :: Apache Software License
Requires-Python: >=3.9
License-File: LICENSE
Requires-Dist: fastcore
Requires-Dist: pandas
Requires-Dist: python-fasthtml
Requires-Dist: monsterui
Requires-Dist: litellm>=1.0.0
Requires-Dist: python-dotenv>=1.0.0
Requires-Dist: aiofiles>=23.0.0
Requires-Dist: lisette
Provides-Extra: dev
Dynamic: author
Dynamic: author-email
Dynamic: classifier
Dynamic: description
Dynamic: description-content-type
Dynamic: home-page
Dynamic: keywords
Dynamic: license
Dynamic: license-file
Dynamic: provides-extra
Dynamic: requires-dist
Dynamic: requires-python
Dynamic: summary
